pyrisco/__init__.py
pyrisco/common.py
pyrisco/cloud/__init__.py
pyrisco/cloud/alarm.py
pyrisco/cloud/event.py
pyrisco/cloud/partition.py
pyrisco/cloud/risco_cloud.py
pyrisco/cloud/zone.py
pyrisco/local/__init__.py
pyrisco/local/const.py
pyrisco/local/panels.py
pyrisco/local/partition.py
pyrisco/local/risco_crypt.py
pyrisco/local/risco_local.py
pyrisco/local/risco_socket.py
pyrisco/local/system.py
pyrisco/local/zone.py
pyrisco-0.6.6.dist-info/LICENSE
pyrisco-0.6.6.dist-info/METADATA
pyrisco-0.6.6.dist-info/WHEEL
pyrisco-0.6.6.dist-info/top_level.txt
pyrisco-0.6.6.dist-info/RECORD
