Metadata-Version: 2.1
Name: pyrisco
Version: 0.6.6
Summary: A python library to communicate with Risco Cloud.
Home-page: https://github.com/OnFreund/PyRisco
Author: On Freund
Author-email: onfreund@gmail.com
License: MIT
Classifier: License :: OSI Approved :: MIT License
Classifier: Programming Language :: Python
Classifier: Programming Language :: Python :: 3
Classifier: Programming Language :: Python :: 3.7
Classifier: Programming Language :: Python :: Implementation :: CPython
Classifier: Programming Language :: Python :: Implementation :: PyPy
Requires-Python: >=3.7.0
License-File: LICENSE
Requires-Dist: aiohttp
